kuka/__init__.py
kuka/_info/__init__.py
kuka/_info/info.py
kuka/_info/texts/matplotlib_api.txt
kuka/_info/texts/pickle.txt
kuka/_info/texts/colors/def_show_named_plotly_colours.txt
kuka/_info/texts/colors/matplotlib_colors.txt
kuka/_info/texts/custom_functions/pdp_plot.txt
kuka/eda/__init__.py
kuka/eda/heatmap_corr.py
kuka/eda/heatmap_correlations.py
kuka/eda/plot_columns_dist.py
kuka/eda/plot_dist.py
kuka/eda/plot_plairplot.py
kuka/eda/plt_missingno_by.py
kuka/eval/__init__.py
kuka/eval/plot/__init__.py
kuka/eval/plot/plot_confusion_matrix.py
kuka/eval/plot/plot_predictions.py
kuka/eval/score/__init__.py
kuka/eval/score/classification_metrics.py
kuka/eval/score/display_score.py
kuka/eval/score/metrics.py
kuka/eval/score/predictions_separate_by_a_variable.py
kuka/interp/__init__.py
kuka/interp/plot/__init__.py
kuka/interp/plot/compare_hists_by.py
kuka/interp/plot/draw_tree.py
kuka/interp/plot/permutation_importance.py
kuka/interp/plot/plot_permutation_importance.py
kuka/interp/plot/plotar_importancias.py
kuka/opt/__init__.py
kuka/opt/optuna_study.py
kuka/preprocess/__init__.py
kuka/preprocess/cat_cols.py
kuka/preprocess/num_cols.py
kuka/utils/__init__.py
kuka/utils/_input_function_validation.py
kuka/utils/_is_valid_path.py
kuka/utils/get_key.py
kuka/utils/imp_exp_pkl.py
kuka/utils/plot/__init__.py
kuka/utils/plot/_adjust_obj_to_ref.py
kuka/utils/plot/_plot_bboxes.py
kuka/utils/plot/_plot_text.py
kuka-0.3.1.3.dist-info/LICENSE
kuka-0.3.1.3.dist-info/METADATA
kuka-0.3.1.3.dist-info/WHEEL
kuka-0.3.1.3.dist-info/top_level.txt
kuka-0.3.1.3.dist-info/RECORD
