Metadata-Version: 2.1
Name: kuka
Version: 0.3.1.3
Summary: Library for EDA, data modeling, and ML modeling analysis/interpretation
Home-page: https://github.com/tenoriolms/kuka_lib
Author: tenoriolms
Classifier: Development Status :: 3 - Alpha
Classifier: Programming Language :: Python :: 3
Classifier: License :: OSI Approved :: BSD License
Classifier: Operating System :: OS Independent
Requires-Python: >=3.6
License-File: LICENSE
Requires-Dist: numpy
Requires-Dist: pandas
Requires-Dist: matplotlib
Requires-Dist: scipy
Requires-Dist: scikit-learn
Requires-Dist: graphviz
Requires-Dist: optuna
Requires-Dist: pathlib
